{"Tables":[{"T84":[{"f1":"CC-TRANS","f2":"Cont. costes de transferencia","f3":"CC-TRANS","f4":""}]},{"T85":[{"f1":"CC-TRANS","f2":"40000","f3":"500","f4":"Total transferencias","f5":"200..300","f6":"Formula","f7":"No","f8":"0","f16":"Yes","f19":"","f20":"","f21":"","f22":"","f23":"No","f24":"No","f25":"No","f26":"No","f27":"Net Change","f28":"Net Amount","f30":"No","f1102":"","f1103":""},{"f1":"CC-TRANS","f2":"30000","f3":"300","f4":"Centros de coste principales","f5":"9902","f6":"Cost Type","f7":"No","f8":"0","f16":"Yes","f19":"","f20":"","f21":"","f22":"","f23":"No","f24":"No","f25":"No","f26":"No","f27":"Net Change","f28":"Net Amount","f30":"No","f1102":"","f1103":""},{"f1":"CC-TRANS","f2":"20000","f3":"200","f4":"Centros de coste iniciales","f5":"9901","f6":"Cost Type","f7":"No","f8":"0","f16":"Yes","f19":"","f20":"","f21":"","f22":"","f23":"No","f24":"No","f25":"No","f26":"No","f27":"Net Change","f28":"Net Amount","f30":"No","f1102":"","f1103":""},{"f1":"CC-TRANS","f2":"10000","f3":"100","f4":"Transferir costes generales","f5":"","f6":"Cost Type","f7":"No","f8":"0","f16":"Yes","f19":"","f20":"","f21":"","f22":"","f23":"No","f24":"No","f25":"No","f26":"No","f27":"Net Change","f28":"Net Amount","f30":"No","f1102":"","f1103":""}]},{"T334":[]}],"Info":{"ID":"CC-TRANS","Module":"FIN","Description":"Account Schedule: Cont. costes de transferencia","Author":"Microsoft","Country":"ES","Version":"14"}}