{"Tables":[{"T84":[{"f1":"I_MINTRIAL","f2":"Data for Reduced Trial Balance Info Part","f3":"PERIODS","f4":"","f10000":""}]},{"T85":[{"f1":"I_MINTRIAL","f2":"10000","f3":"10","f4":"Total Revenue","G5":{"f1":"49950","f2":"Total Revenue","f3":"TOTAL REVENUE","f4":"4","f6":"","f7":"","f8":"1","f9":"0","f10":"0","f11":"","f13":"false","f14":"false","f16":"false","f17":"false","f18":"0","f19":"0","f25":"","f26":"","f34":"40000..49950","f39":"0","f40":"","f41":"","f43":"0","f44":"","f45":"","f46":" ","f49":"false","f54":"","f55":"false","f56":"","f57":"","f58":"","f63":"0","f66":"","f70":"false","f80":"8","f1100":"","f1700":"","f8000":"{9B658433-F687-4C5B-AFC3-6C78FF617425}","f10001":"","f27000":"","Totals":""},"f6":"1","f7":"false","f8":"0","f16":"0","f19":"","f20":"","f21":"","f22":"","f23":"false","f24":"false","f25":"false","f26":"true","f27":"0","f28":"0","f30":"false","f1102":"","f1103":""},{"f1":"I_MINTRIAL","f2":"20000","f3":"20","f4":"Total Cost","G5":{"f1":"59950","f2":"Total Cost","f3":"TOTAL COST","f4":"4","f6":"","f7":"","f8":"1","f9":"0","f10":"0","f11":"","f13":"false","f14":"false","f16":"false","f17":"false","f18":"0","f19":"0","f25":"","f26":"","f34":"50000..59950","f39":"0","f40":"","f41":"","f43":"0","f44":"","f45":"","f46":" ","f49":"false","f54":"","f55":"false","f56":"","f57":"","f58":"","f63":"0","f66":"","f70":"false","f80":"8","f1100":"","f1700":"","f8000":"{7E351161-9CF3-4B56-98C3-63B8B738F849}","f10001":"","f27000":"","Totals":""},"f6":"1","f7":"false","f8":"0","f16":"0","f19":"","f20":"","f21":"","f22":"","f23":"false","f24":"false","f25":"false","f26":"true","f27":"0","f28":"0","f30":"false","f1102":"","f1103":""},{"f1":"I_MINTRIAL","f2":"30000","f3":"30","f4":"Gross Margin","f5":"-10-20","f6":"2","f7":"false","f8":"0","f16":"0","f19":"","f20":"","f21":"","f22":"","f23":"false","f24":"false","f25":"false","f26":"false","f27":"0","f28":"0","f30":"false","f1102":"","f1103":""},{"f1":"I_MINTRIAL","f2":"40000","f3":"40","f4":"Gross Margin %","f5":"-'30'/'10'*100","f6":"2","f7":"false","f8":"0","f16":"0","f19":"","f20":"","f21":"","f22":"","f23":"false","f24":"false","f25":"false","f26":"false","f27":"0","f28":"0","f30":"false","f1102":"","f1103":""},{"f1":"I_MINTRIAL","f2":"50000","f3":"50","f4":"Operating Expenses","f6":"1","f7":"false","f8":"0","f16":"0","f19":"","f20":"","f21":"","f22":"","f23":"false","f24":"false","f25":"false","f26":"false","f27":"0","f28":"0","f30":"false","f1102":"","f1103":""},{"f1":"I_MINTRIAL","f2":"60000","f3":"60","f4":"Operating Margin","f5":"30 - 50","f6":"2","f7":"false","f8":"0","f16":"0","f19":"","f20":"","f21":"","f22":"","f23":"false","f24":"false","f25":"false","f26":"false","f27":"0","f28":"0","f30":"false","f1102":"","f1103":""},{"f1":"I_MINTRIAL","f2":"70000","f3":"70","f4":"Operating Margin %","f5":"-'60'/'10'*100","f6":"2","f7":"false","f8":"0","f16":"0","f19":"","f20":"","f21":"","f22":"","f23":"false","f24":"false","f25":"false","f26":"false","f27":"0","f28":"0","f30":"false","f1102":"","f1103":""},{"f1":"I_MINTRIAL","f2":"80000","f3":"80","f4":"Other Expenses","G5":{"f1":"67500","f2":"Other Costs of Operations","f3":"OTHER COSTS OF OPERATIONS","f4":"0","f6":"","f7":"","f8":"6","f9":"0","f10":"0","f11":"","f13":"false","f14":"true","f16":"false","f17":"false","f18":"0","f19":"2","f25":"","f26":"","f34":"","f39":"0","f40":"","f41":"","f43":"1","f44":"","f45":"MISC","f46":" ","f49":"false","f54":"","f55":"false","f56":"NONTAXABLE","f57":"","f58":"","f63":"0","f66":"","f70":"false","f80":"42","f1100":"67500","f1700":"","f8000":"{330360B5-76DF-49B4-983B-0F1652DB3942}","f10001":"","f27000":"","Totals":"Other Operating Expenses,Operating Expenses"},"f6":"0","f7":"false","f8":"0","f16":"0","f19":"","f20":"","f21":"","f22":"","f23":"false","f24":"false","f25":"false","f26":"false","f27":"0","f28":"0","f30":"false","f1102":"","f1103":""},{"f1":"I_MINTRIAL","f2":"90000","f3":"90","f4":"Income before Interest and Tax","G5":{"f1":"69999","f2":"Net Operating Income","f3":"NET OPERATING INCOME","f4":"2","f6":"","f7":"","f8":"1","f9":"0","f10":"0","f11":"","f13":"false","f14":"false","f16":"false","f17":"false","f18":"1","f19":"0","f25":"","f26":"","f34":"40000..69999","f39":"0","f40":"","f41":"","f43":"0","f44":"","f45":"","f46":" ","f49":"false","f54":"","f55":"false","f56":"","f57":"","f58":"","f63":"0","f66":"","f70":"false","f80":"8","f1100":"","f1700":"","f8000":"{DA9A9B7B-249B-4B26-95F9-DA0AD166B49D}","f10001":"","f27000":"","Totals":""},"f6":"1","f7":"false","f8":"0","f16":"0","f19":"","f20":"","f21":"","f22":"","f23":"false","f24":"false","f25":"false","f26":"true","f27":"0","f28":"0","f30":"false","f1102":"","f1103":""}]},{"T334":[{"f1":"PERIODS","f2":"10000","f3":"10","f4":"CURRENT PERIOD","f5":"1","f6":"0","f7":"0","f8":"","f9":"","f10":"false","f11":"0","f12":"0","f13":"0","f14":"","f15":"","f16":"","f17":"","f18":"","f19":"","f20":"","f21":"","f30":"1033"},{"f1":"PERIODS","f2":"20000","f3":"10","f4":"CURRENT PERIOD - 1","f5":"1","f6":"0","f7":"0","f8":"","f9":"","f10":"false","f11":"0","f12":"0","f13":"0","f14":"-1P","f15":"","f16":"","f17":"","f18":"","f19":"","f20":"","f21":"","f30":"1033"},{"f1":"PERIODS","f2":"30000","f3":"10","f4":"CURRENT PERIOD - 2","f5":"1","f6":"0","f7":"0","f8":"","f9":"","f10":"false","f11":"0","f12":"0","f13":"0","f14":"-2P","f15":"","f16":"","f17":"","f18":"","f19":"","f20":"","f21":"","f30":"1033"}]}],"Info":{"ID":"I_MINTRIAL","Module":"FIN","Description":"Account Schedule: Data for Reduced Trial Balance Info Part","Author":"Microsoft","Country":"US","Version":"US Dynamics NAV 13.4"}}