{"Tables":[{"T323":[{"f1":"EXPORT","f2":"Klanten/leveranciers (niet EU)","f10":"","f8000":"{5277F35E-D6AC-40D7-BE57-D833734F93CD}"},{"f1":"EU","f2":"Klanten/leveranciers (EU)","f10":"","f8000":"{A0E70ECE-6F12-49A5-B887-8C55B39632E4}"},{"f1":"BINNENLAND","f2":"Klanten/leveranciers (binnenland)","f10":"","f8000":"{865C67DE-543C-4801-9E34-8CB2B4BB5C61}"}]},{"T324":[{"f1":"ZERO","f2":"Geen btw","f8000":"{0F44EE35-116D-46E7-B98B-9C48091BA66D}","f8005":""},{"f1":"STANDAARD","f2":"Standaard-btw (21%)","f8000":"{896A8CBC-8573-4097-94C1-23E0F0AF3F92}","f8005":""},{"f1":"SERV RED","f2":"Diversen 6 btw","f8000":"{1D7E4271-D0F0-4F29-B116-FB98CFBB37B3}","f8005":""},{"f1":"SERV NORM","f2":"Diversen 21 btw","f8000":"{5A98A29F-5040-4F04-B0F1-FE52A477A1E8}","f8005":""},{"f1":"GEREDUC.","f2":"Gereduceerde btw (6%)","f8000":"{F2867A73-A26D-4497-9A83-6A874C5CA1EF}","f8005":""},{"f1":"FULL RED","f2":"Alleen btw-facturen 6%","f8000":"{0AA9FC11-9FA7-482E-B67C-60FBE7CD6502}","f8005":""},{"f1":"FULL NORM","f2":"Alleen btw-facturen 21%","f8000":"{355FDFD2-7DAD-4869-9246-CDC9BD2E534C}","f8005":""}]},{"T325":[{"f1":"EXPORT","f2":"ZERO","f3":"Normal VAT","f4":"0","f5":" ","f6":"No","G7":{"Filter":"%1","Accounts":[{"f1":"G1514","f2":"Verk.-btw 0% EU","f3":"VERK.-BTW 0% EU","f4":"Posting","f6":"","f7":"","f8":"Liabilities","f9":"Balance Sheet","f10":"Both","f11":"","f13":"No","f14":"Yes","f16":"No","f17":"No","f18":"0","f19":"1","f25":"","f34":"","f39":"Average Rate (Manual)","f40":"","f41":"","f43":" ","f44":"","f45":"","f46":"","f49":"No","f54":"","f55":"No","f56":"","f57":"","f58":"","f63":"No Adjustment","f66":"","f70":"No","f80":"11","f1100":"","f1700":"","f8000":"{5F020CA5-CFE4-4113-B386-752067BC26FA}","Totals":""}]},"G9":{"Filter":"%1","Accounts":[{"f1":"G1519","f2":"Ink.-btw 0% EU","f3":"INK.-BTW 0% EU","f4":"Posting","f6":"","f7":"","f8":"Liabilities","f9":"Balance Sheet","f10":"Both","f11":"","f13":"No","f14":"Yes","f16":"No","f17":"No","f18":"0","f19":"1","f25":"","f34":"","f39":"Average Rate (Manual)","f40":"","f41":"","f43":" ","f44":"","f45":"","f46":"","f49":"No","f54":"","f55":"No","f56":"","f57":"","f58":"","f63":"No Adjustment","f66":"","f70":"No","f80":"11","f1100":"","f1700":"","f8000":"{F34677FF-DACD-403A-9018-9329C9A36E49}","Totals":""}]},"f13":"ZERO","f14":"No","f15":"ZERO","f16":"No","f17":"E","f20":"Instellen voor EXPORT / ZERO"},{"f1":"EXPORT","f2":"STANDAARD","f3":"Normal VAT","f4":"0","f5":" ","f6":"No","G7":{"Filter":"%1","Accounts":[{"f1":"G1513","f2":"Verk.-btw 21%","f3":"VERK.-BTW 21%","f4":"Posting","f6":"","f7":"","f8":"Liabilities","f9":"Balance Sheet","f10":"Both","f11":"","f13":"No","f14":"Yes","f16":"No","f17":"No","f18":"0","f19":"1","f25":"","f34":"","f39":"Average Rate (Manual)","f40":"","f41":"","f43":" ","f44":"","f45":"","f46":"","f49":"No","f54":"","f55":"No","f56":"","f57":"","f58":"","f63":"No Adjustment","f66":"","f70":"No","f80":"11","f1100":"","f1700":"","f8000":"{61F92658-9AA8-414E-A14E-9901832CFC55}","Totals":""}]},"G9":{"Filter":"%1","Accounts":[{"f1":"G1518","f2":"Ink.-btw 21%","f3":"INK.-BTW 21%","f4":"Posting","f6":"","f7":"","f8":"Liabilities","f9":"Balance Sheet","f10":"Both","f11":"","f13":"No","f14":"Yes","f16":"No","f17":"No","f18":"0","f19":"1","f25":"","f34":"","f39":"Average Rate (Manual)","f40":"","f41":"","f43":" ","f44":"","f45":"","f46":"","f49":"No","f54":"","f55":"No","f56":"","f57":"","f58":"","f63":"No Adjustment","f66":"","f70":"No","f80":"11","f1100":"","f1700":"","f8000":"{02F8AD36-90AA-43B1-A269-A56F9C7E051F}","Totals":""}]},"f13":"STANDAARD","f14":"No","f15":"","f16":"No","f17":"E","f20":"Instellen voor EXPORT / STANDAARD"},{"f1":"EXPORT","f2":"GEREDUC.","f3":"Normal VAT","f4":"0","f5":" ","f6":"No","G7":{"Filter":"%1","Accounts":[{"f1":"G1510","f2":"Verk.-btw 6%","f3":"VERK.-BTW 6%","f4":"Posting","f6":"","f7":"","f8":"Liabilities","f9":"Balance Sheet","f10":"Both","f11":"","f13":"No","f14":"Yes","f16":"No","f17":"No","f18":"0","f19":"1","f25":"","f34":"","f39":"Average Rate (Manual)","f40":"","f41":"","f43":" ","f44":"","f45":"","f46":"","f49":"No","f54":"","f55":"No","f56":"","f57":"","f58":"","f63":"No Adjustment","f66":"","f70":"No","f80":"11","f1100":"","f1700":"","f8000":"{2E6E51B9-6F71-4873-A239-A196A7D8111E}","Totals":""}]},"G9":{"Filter":"%1","Accounts":[{"f1":"G1515","f2":"Ink.-btw 6%","f3":"INK.-BTW 6%","f4":"Posting","f6":"","f7":"","f8":"Liabilities","f9":"Balance Sheet","f10":"Both","f11":"","f13":"No","f14":"Yes","f16":"No","f17":"No","f18":"0","f19":"1","f25":"","f34":"","f39":"Average Rate (Manual)","f40":"","f41":"","f43":" ","f44":"","f45":"","f46":"","f49":"No","f54":"","f55":"No","f56":"","f57":"","f58":"","f63":"No Adjustment","f66":"","f70":"No","f80":"11","f1100":"","f1700":"","f8000":"{0862686D-34F8-439F-9F80-33D5E95B725D}","Totals":""}]},"f13":"GEREDUC.","f14":"No","f15":"","f16":"No","f17":"E","f20":"Instellen voor EXPORT / GEREDUC."},{"f1":"EU","f2":"ZERO","f3":"Normal VAT","f4":"0","f5":" ","f6":"No","G7":{"Filter":"%1","Accounts":[{"f1":"G1514","f2":"Verk.-btw 0% EU","f3":"VERK.-BTW 0% EU","f4":"Posting","f6":"","f7":"","f8":"Liabilities","f9":"Balance Sheet","f10":"Both","f11":"","f13":"No","f14":"Yes","f16":"No","f17":"No","f18":"0","f19":"1","f25":"","f34":"","f39":"Average Rate (Manual)","f40":"","f41":"","f43":" ","f44":"","f45":"","f46":"","f49":"No","f54":"","f55":"No","f56":"","f57":"","f58":"","f63":"No Adjustment","f66":"","f70":"No","f80":"11","f1100":"","f1700":"","f8000":"{5F020CA5-CFE4-4113-B386-752067BC26FA}","Totals":""}]},"G9":{"Filter":"%1","Accounts":[{"f1":"G1519","f2":"Ink.-btw 0% EU","f3":"INK.-BTW 0% EU","f4":"Posting","f6":"","f7":"","f8":"Liabilities","f9":"Balance Sheet","f10":"Both","f11":"","f13":"No","f14":"Yes","f16":"No","f17":"No","f18":"0","f19":"1","f25":"","f34":"","f39":"Average Rate (Manual)","f40":"","f41":"","f43":" ","f44":"","f45":"","f46":"","f49":"No","f54":"","f55":"No","f56":"","f57":"","f58":"","f63":"No Adjustment","f66":"","f70":"No","f80":"11","f1100":"","f1700":"","f8000":"{F34677FF-DACD-403A-9018-9329C9A36E49}","Totals":""}]},"f13":"ZERO","f14":"No","f15":"ZERO","f16":"No","f17":"E","f20":"Instellen voor EU / ZERO"},{"f1":"EU","f2":"STANDAARD","f3":"Reverse Charge VAT","f4":"21","f5":" ","f6":"No","G7":{"Filter":"%1","Accounts":[{"f1":"G1513","f2":"Verk.-btw 21%","f3":"VERK.-BTW 21%","f4":"Posting","f6":"","f7":"","f8":"Liabilities","f9":"Balance Sheet","f10":"Both","f11":"","f13":"No","f14":"Yes","f16":"No","f17":"No","f18":"0","f19":"1","f25":"","f34":"","f39":"Average Rate (Manual)","f40":"","f41":"","f43":" ","f44":"","f45":"","f46":"","f49":"No","f54":"","f55":"No","f56":"","f57":"","f58":"","f63":"No Adjustment","f66":"","f70":"No","f80":"11","f1100":"","f1700":"","f8000":"{61F92658-9AA8-414E-A14E-9901832CFC55}","Totals":""}]},"G9":{"Filter":"%1","Accounts":[{"f1":"G1518","f2":"Ink.-btw 21%","f3":"INK.-BTW 21%","f4":"Posting","f6":"","f7":"","f8":"Liabilities","f9":"Balance Sheet","f10":"Both","f11":"","f13":"No","f14":"Yes","f16":"No","f17":"No","f18":"0","f19":"1","f25":"","f34":"","f39":"Average Rate (Manual)","f40":"","f41":"","f43":" ","f44":"","f45":"","f46":"","f49":"No","f54":"","f55":"No","f56":"","f57":"","f58":"","f63":"No Adjustment","f66":"","f70":"No","f80":"11","f1100":"","f1700":"","f8000":"{02F8AD36-90AA-43B1-A269-A56F9C7E051F}","Totals":""}]},"G11":{"Filter":"%1","Accounts":[{"f1":"G1518","f2":"Ink.-btw 21%","f3":"INK.-BTW 21%","f4":"Posting","f6":"","f7":"","f8":"Liabilities","f9":"Balance Sheet","f10":"Both","f11":"","f13":"No","f14":"Yes","f16":"No","f17":"No","f18":"0","f19":"1","f25":"","f34":"","f39":"Average Rate (Manual)","f40":"","f41":"","f43":" ","f44":"","f45":"","f46":"","f49":"No","f54":"","f55":"No","f56":"","f57":"","f58":"","f63":"No Adjustment","f66":"","f70":"No","f80":"11","f1100":"","f1700":"","f8000":"{02F8AD36-90AA-43B1-A269-A56F9C7E051F}","Totals":""}]},"f13":"STANDAARD","f14":"No","f15":"","f16":"No","f17":"S","f20":"Instellen voor EU / STANDAARD"},{"f1":"EU","f2":"GEREDUC.","f3":"Reverse Charge VAT","f4":"6","f5":" ","f6":"No","G7":{"Filter":"%1","Accounts":[{"f1":"G1510","f2":"Verk.-btw 6%","f3":"VERK.-BTW 6%","f4":"Posting","f6":"","f7":"","f8":"Liabilities","f9":"Balance Sheet","f10":"Both","f11":"","f13":"No","f14":"Yes","f16":"No","f17":"No","f18":"0","f19":"1","f25":"","f34":"","f39":"Average Rate (Manual)","f40":"","f41":"","f43":" ","f44":"","f45":"","f46":"","f49":"No","f54":"","f55":"No","f56":"","f57":"","f58":"","f63":"No Adjustment","f66":"","f70":"No","f80":"11","f1100":"","f1700":"","f8000":"{2E6E51B9-6F71-4873-A239-A196A7D8111E}","Totals":""}]},"G9":{"Filter":"%1","Accounts":[{"f1":"G1515","f2":"Ink.-btw 6%","f3":"INK.-BTW 6%","f4":"Posting","f6":"","f7":"","f8":"Liabilities","f9":"Balance Sheet","f10":"Both","f11":"","f13":"No","f14":"Yes","f16":"No","f17":"No","f18":"0","f19":"1","f25":"","f34":"","f39":"Average Rate (Manual)","f40":"","f41":"","f43":" ","f44":"","f45":"","f46":"","f49":"No","f54":"","f55":"No","f56":"","f57":"","f58":"","f63":"No Adjustment","f66":"","f70":"No","f80":"11","f1100":"","f1700":"","f8000":"{0862686D-34F8-439F-9F80-33D5E95B725D}","Totals":""}]},"G11":{"Filter":"%1","Accounts":[{"f1":"G1516","f2":"Ink.-btw 6% EU","f3":"INK.-BTW 6% EU","f4":"Posting","f6":"","f7":"","f8":"Liabilities","f9":"Balance Sheet","f10":"Both","f11":"","f13":"No","f14":"Yes","f16":"No","f17":"No","f18":"0","f19":"1","f25":"","f34":"","f39":"Average Rate (Manual)","f40":"","f41":"","f43":" ","f44":"","f45":"","f46":"","f49":"No","f54":"","f55":"No","f56":"","f57":"","f58":"","f63":"No Adjustment","f66":"","f70":"No","f80":"11","f1100":"","f1700":"","f8000":"{270833C5-5F5E-406C-A611-6D6D67E9DCE8}","Totals":""}]},"f13":"GEREDUC.","f14":"Yes","f15":"","f16":"No","f17":"S","f20":"Instellen voor EU / GEREDUC."},{"f1":"BINNENLAND","f2":"ZERO","f3":"Normal VAT","f4":"0","f5":" ","f6":"No","G7":{"Filter":"%1","Accounts":[{"f1":"G1514","f2":"Verk.-btw 0% EU","f3":"VERK.-BTW 0% EU","f4":"Posting","f6":"","f7":"","f8":"Liabilities","f9":"Balance Sheet","f10":"Both","f11":"","f13":"No","f14":"Yes","f16":"No","f17":"No","f18":"0","f19":"1","f25":"","f34":"","f39":"Average Rate (Manual)","f40":"","f41":"","f43":" ","f44":"","f45":"","f46":"","f49":"No","f54":"","f55":"No","f56":"","f57":"","f58":"","f63":"No Adjustment","f66":"","f70":"No","f80":"11","f1100":"","f1700":"","f8000":"{5F020CA5-CFE4-4113-B386-752067BC26FA}","Totals":""}]},"G9":{"Filter":"%1","Accounts":[{"f1":"G1519","f2":"Ink.-btw 0% EU","f3":"INK.-BTW 0% EU","f4":"Posting","f6":"","f7":"","f8":"Liabilities","f9":"Balance Sheet","f10":"Both","f11":"","f13":"No","f14":"Yes","f16":"No","f17":"No","f18":"0","f19":"1","f25":"","f34":"","f39":"Average Rate (Manual)","f40":"","f41":"","f43":" ","f44":"","f45":"","f46":"","f49":"No","f54":"","f55":"No","f56":"","f57":"","f58":"","f63":"No Adjustment","f66":"","f70":"No","f80":"11","f1100":"","f1700":"","f8000":"{F34677FF-DACD-403A-9018-9329C9A36E49}","Totals":""}]},"f13":"ZERO","f14":"No","f15":"ZERO","f16":"No","f17":"E","f20":"Instellen voor BINNENLAND / ZERO"},{"f1":"BINNENLAND","f2":"STANDAARD","f3":"Normal VAT","f4":"21","f5":" ","f6":"No","G7":{"Filter":"%1","Accounts":[{"f1":"G1513","f2":"Verk.-btw 21%","f3":"VERK.-BTW 21%","f4":"Posting","f6":"","f7":"","f8":"Liabilities","f9":"Balance Sheet","f10":"Both","f11":"","f13":"No","f14":"Yes","f16":"No","f17":"No","f18":"0","f19":"1","f25":"","f34":"","f39":"Average Rate (Manual)","f40":"","f41":"","f43":" ","f44":"","f45":"","f46":"","f49":"No","f54":"","f55":"No","f56":"","f57":"","f58":"","f63":"No Adjustment","f66":"","f70":"No","f80":"11","f1100":"","f1700":"","f8000":"{61F92658-9AA8-414E-A14E-9901832CFC55}","Totals":""}]},"G9":{"Filter":"%1","Accounts":[{"f1":"G1518","f2":"Ink.-btw 21%","f3":"INK.-BTW 21%","f4":"Posting","f6":"","f7":"","f8":"Liabilities","f9":"Balance Sheet","f10":"Both","f11":"","f13":"No","f14":"Yes","f16":"No","f17":"No","f18":"0","f19":"1","f25":"","f34":"","f39":"Average Rate (Manual)","f40":"","f41":"","f43":" ","f44":"","f45":"","f46":"","f49":"No","f54":"","f55":"No","f56":"","f57":"","f58":"","f63":"No Adjustment","f66":"","f70":"No","f80":"11","f1100":"","f1700":"","f8000":"{02F8AD36-90AA-43B1-A269-A56F9C7E051F}","Totals":""}]},"f13":"STANDAARD","f14":"No","f15":"","f16":"No","f17":"S","f20":"Instellen voor BINNENLAND / STANDAARD"},{"f1":"BINNENLAND","f2":"GEREDUC.","f3":"Normal VAT","f4":"6","f5":" ","f6":"No","G7":{"Filter":"%1","Accounts":[{"f1":"G1510","f2":"Verk.-btw 6%","f3":"VERK.-BTW 6%","f4":"Posting","f6":"","f7":"","f8":"Liabilities","f9":"Balance Sheet","f10":"Both","f11":"","f13":"No","f14":"Yes","f16":"No","f17":"No","f18":"0","f19":"1","f25":"","f34":"","f39":"Average Rate (Manual)","f40":"","f41":"","f43":" ","f44":"","f45":"","f46":"","f49":"No","f54":"","f55":"No","f56":"","f57":"","f58":"","f63":"No Adjustment","f66":"","f70":"No","f80":"11","f1100":"","f1700":"","f8000":"{2E6E51B9-6F71-4873-A239-A196A7D8111E}","Totals":""}]},"G9":{"Filter":"%1","Accounts":[{"f1":"G1515","f2":"Ink.-btw 6%","f3":"INK.-BTW 6%","f4":"Posting","f6":"","f7":"","f8":"Liabilities","f9":"Balance Sheet","f10":"Both","f11":"","f13":"No","f14":"Yes","f16":"No","f17":"No","f18":"0","f19":"1","f25":"","f34":"","f39":"Average Rate (Manual)","f40":"","f41":"","f43":" ","f44":"","f45":"","f46":"","f49":"No","f54":"","f55":"No","f56":"","f57":"","f58":"","f63":"No Adjustment","f66":"","f70":"No","f80":"11","f1100":"","f1700":"","f8000":"{0862686D-34F8-439F-9F80-33D5E95B725D}","Totals":""}]},"f13":"GEREDUC.","f14":"No","f15":"","f16":"No","f17":"S","f20":"Instellen voor BINNENLAND / GEREDUC."},{"f1":"","f2":"ZERO","f3":"Normal VAT","f4":"0","f5":" ","f6":"No","G7":{"Filter":"%1","Accounts":[{"f1":"G1514","f2":"Verk.-btw 0% EU","f3":"VERK.-BTW 0% EU","f4":"Posting","f6":"","f7":"","f8":"Liabilities","f9":"Balance Sheet","f10":"Both","f11":"","f13":"No","f14":"Yes","f16":"No","f17":"No","f18":"0","f19":"1","f25":"","f34":"","f39":"Average Rate (Manual)","f40":"","f41":"","f43":" ","f44":"","f45":"","f46":"","f49":"No","f54":"","f55":"No","f56":"","f57":"","f58":"","f63":"No Adjustment","f66":"","f70":"No","f80":"11","f1100":"","f1700":"","f8000":"{5F020CA5-CFE4-4113-B386-752067BC26FA}","Totals":""}]},"G9":{"Filter":"%1","Accounts":[{"f1":"G1519","f2":"Ink.-btw 0% EU","f3":"INK.-BTW 0% EU","f4":"Posting","f6":"","f7":"","f8":"Liabilities","f9":"Balance Sheet","f10":"Both","f11":"","f13":"No","f14":"Yes","f16":"No","f17":"No","f18":"0","f19":"1","f25":"","f34":"","f39":"Average Rate (Manual)","f40":"","f41":"","f43":" ","f44":"","f45":"","f46":"","f49":"No","f54":"","f55":"No","f56":"","f57":"","f58":"","f63":"No Adjustment","f66":"","f70":"No","f80":"11","f1100":"","f1700":"","f8000":"{F34677FF-DACD-403A-9018-9329C9A36E49}","Totals":""}]},"f13":"ZERO","f14":"No","f15":"ZERO","f16":"No","f17":"E","f20":"Instellen voor  / ZERO"},{"f1":"","f2":"STANDAARD","f3":"Normal VAT","f4":"0","f5":" ","f6":"No","G7":{"Filter":"%1","Accounts":[{"f1":"G1513","f2":"Verk.-btw 21%","f3":"VERK.-BTW 21%","f4":"Posting","f6":"","f7":"","f8":"Liabilities","f9":"Balance Sheet","f10":"Both","f11":"","f13":"No","f14":"Yes","f16":"No","f17":"No","f18":"0","f19":"1","f25":"","f34":"","f39":"Average Rate (Manual)","f40":"","f41":"","f43":" ","f44":"","f45":"","f46":"","f49":"No","f54":"","f55":"No","f56":"","f57":"","f58":"","f63":"No Adjustment","f66":"","f70":"No","f80":"11","f1100":"","f1700":"","f8000":"{61F92658-9AA8-414E-A14E-9901832CFC55}","Totals":""}]},"G9":{"Filter":"%1","Accounts":[{"f1":"G1518","f2":"Ink.-btw 21%","f3":"INK.-BTW 21%","f4":"Posting","f6":"","f7":"","f8":"Liabilities","f9":"Balance Sheet","f10":"Both","f11":"","f13":"No","f14":"Yes","f16":"No","f17":"No","f18":"0","f19":"1","f25":"","f34":"","f39":"Average Rate (Manual)","f40":"","f41":"","f43":" ","f44":"","f45":"","f46":"","f49":"No","f54":"","f55":"No","f56":"","f57":"","f58":"","f63":"No Adjustment","f66":"","f70":"No","f80":"11","f1100":"","f1700":"","f8000":"{02F8AD36-90AA-43B1-A269-A56F9C7E051F}","Totals":""}]},"f13":"STANDAARD","f14":"No","f15":"","f16":"No","f17":"E","f20":"Instellen voor  / STANDAARD"},{"f1":"","f2":"GEREDUC.","f3":"Normal VAT","f4":"0","f5":" ","f6":"No","G7":{"Filter":"%1","Accounts":[{"f1":"G1510","f2":"Verk.-btw 6%","f3":"VERK.-BTW 6%","f4":"Posting","f6":"","f7":"","f8":"Liabilities","f9":"Balance Sheet","f10":"Both","f11":"","f13":"No","f14":"Yes","f16":"No","f17":"No","f18":"0","f19":"1","f25":"","f34":"","f39":"Average Rate (Manual)","f40":"","f41":"","f43":" ","f44":"","f45":"","f46":"","f49":"No","f54":"","f55":"No","f56":"","f57":"","f58":"","f63":"No Adjustment","f66":"","f70":"No","f80":"11","f1100":"","f1700":"","f8000":"{2E6E51B9-6F71-4873-A239-A196A7D8111E}","Totals":""}]},"G9":{"Filter":"%1","Accounts":[{"f1":"G1515","f2":"Ink.-btw 6%","f3":"INK.-BTW 6%","f4":"Posting","f6":"","f7":"","f8":"Liabilities","f9":"Balance Sheet","f10":"Both","f11":"","f13":"No","f14":"Yes","f16":"No","f17":"No","f18":"0","f19":"1","f25":"","f34":"","f39":"Average Rate (Manual)","f40":"","f41":"","f43":" ","f44":"","f45":"","f46":"","f49":"No","f54":"","f55":"No","f56":"","f57":"","f58":"","f63":"No Adjustment","f66":"","f70":"No","f80":"11","f1100":"","f1700":"","f8000":"{0862686D-34F8-439F-9F80-33D5E95B725D}","Totals":""}]},"f13":"GEREDUC.","f14":"No","f15":"","f16":"No","f17":"E","f20":"Instellen voor  / GEREDUC."}]}],"Info":{"ID":"SALES_TAX.standard","Module":"SALE","Description":"Sales Tax standard (NL)","Author":"Microsoft","Country":"NL","Version":"14"}}